zeg/__init__.py
zeg/__main__.py
zeg/auth.py
zeg/azure_blobs.py
zeg/collections.py
zeg/config.py
zeg/datasets.py
zeg/http.py
zeg/imagesets.py
zeg/log.py
zeg/projects.py
zeg/sql.py
zeg/schemata/spec.yaml
zeg/tests/__init__.py
zeg/tests/test_collections.py
zeg/tests/test_config.py
zeg/tests/test_http.py
zeg/tests/test_imagesets.py
zegami_cli-1.5.1.dist-info/LICENSE
zegami_cli-1.5.1.dist-info/METADATA
zegami_cli-1.5.1.dist-info/WHEEL
zegami_cli-1.5.1.dist-info/entry_points.txt
zegami_cli-1.5.1.dist-info/top_level.txt
zegami_cli-1.5.1.dist-info/RECORD
