Metadata-Version: 2.1
Name: zegami-cli
Version: 1.5.1
Summary: Command Line Interface for Zegami
Home-page: https://github.com/zegami/zegami-cli
Author: Zegami
Author-email: help@zegami.com
License: UNKNOWN
Project-URL: Zegami, https://zegami.com
Project-URL: Bug Reports, https://github.com/zegami/zegami-cli/issues
Platform: UNKNOWN
Classifier: Development Status :: 4 - Beta
Classifier: Intended Audience :: Developers
Classifier: Topic :: Software Development :: User Interfaces
Classifier: License :: OSI Approved :: Apache Software License
Classifier: Programming Language :: Python :: 3
Classifier: Programming Language :: Python :: 3.6
Classifier: Programming Language :: Python :: 3.7
Classifier: Programming Language :: Python :: 3.8
License-File: LICENSE
Requires-Dist: appdirs (==1.4.3)
Requires-Dist: azure-storage-blob (==12.3.0)
Requires-Dist: colorama (==0.4.3)
Requires-Dist: jsonschema (==3.2.0)
Requires-Dist: PyYaml (==5.4)
Requires-Dist: requests (<3.0,>=2.15.0)
Requires-Dist: tqdm (==4.43.0)
Provides-Extra: sql
Requires-Dist: pyodbc (==4.0.30) ; extra == 'sql'
Requires-Dist: SQLAlchemy (==1.3.15) ; extra == 'sql'
